swi_prolog_kernel/__init__.py
swi_prolog_kernel/__main__.py
swi_prolog_kernel/kernel.json
swi_prolog_kernel/kernel.py
jupyter_swi_prolog-1.0.2.1.dist-info/METADATA
jupyter_swi_prolog-1.0.2.1.dist-info/WHEEL
jupyter_swi_prolog-1.0.2.1.dist-info/top_level.txt
jupyter_swi_prolog-1.0.2.1.dist-info/RECORD
