Metadata-Version: 2.1
Name: jupyter-swi-prolog
Version: 1.0.2.1
Summary: a basic wrapper kernel for SWI-Prolog
Home-page: https://github.com/erictroebs/jupyter-swi-prolog
Author: Eric Tröbs
Author-email: eric.troebs@tu-ilmenau.de
Project-URL: Bug Tracker, https://github.com/erictroebs/jupyter-swi-prolog/issues
Classifier: Programming Language :: Python :: 3
Classifier: License :: OSI Approved :: MIT License
Classifier: Operating System :: OS Independent
Requires-Python: >=3.7
Requires-Dist: jupyter
Requires-Dist: swiplserver ~=1.0.2
